bresenham.py
bresenham-0.2.dist-info/DESCRIPTION.rst
bresenham-0.2.dist-info/METADATA
bresenham-0.2.dist-info/RECORD
bresenham-0.2.dist-info/WHEEL
bresenham-0.2.dist-info/metadata.json
bresenham-0.2.dist-info/top_level.txt
