Metadata-Version: 2.0
Name: bresenham
Version: 0.2
Summary: An implementation of Bresenham's line drawing algorithm
Home-page: https://github.com/encukou/bresenham
Author: Petr Viktorin
Author-email: encukou@gmail.com
License: MIT
Keywords: bresenham,pixel art
Platform: UNKNOWN
Classifier: Intended Audience :: Developers
Classifier: License :: OSI Approved :: MIT License
Classifier: Operating System :: POSIX :: Linux
Classifier: Programming Language :: Python
Classifier: Programming Language :: Python :: Implementation :: CPython
Classifier: Programming Language :: Python :: 3
Classifier: Programming Language :: Python :: 3.5
Classifier: Topic :: Software Development :: Libraries
